word4univer/__init__.py
word4univer/Info/__init__.py
word4univer/Info/lab_info.py
word4univer/Info/student_info.py
word4univer/Info/subject_info.py
word4univer/Lab/__init__.py
word4univer/Lab/inputs.py
word4univer/Lab/lab.py
word4univer/Name/__init__.py
word4univer/Name/full_name.py
word4univer/Name/name_pattern.py
word4univer/Path/__init__.py
word4univer/Path/src_path.py
word4univer/Path/Utils/__init__.py
word4univer/Path/Utils/path_utils.py
word4univer/TitlePages/__init__.py
word4univer/TitlePages/timp.py
word4univer/TitlePages/tstu.py
word4univer/Word/__init__.py
word4univer/Word/document.py
word4univer/Word/rels/__init__.py
word4univer/Word/rels/image.py
word4univer/Word/rels/relation.py
word4univer/Word/rels/xml.py
word4univer/src/docparts/image.xml
word4univer/src/docparts/footers/default.xml
word4univer/src/docparts/footers/first.xml
word4univer/src/docparts/title_pages/TSTU.xml
word4univer/src/docparts/title_pages/TiMP.xml
word4univer/src/empty_doc/[Content_Types].xml
word4univer/src/empty_doc/_rels/.rels
word4univer/src/empty_doc/word/document.xml
word4univer/src/empty_doc/word/_rels/document.xml.rels
word4univer/src/images/tstu.wmf
word4univer/src/styles/default.xml
word4univer/src/styles/tstu.xml
word4univer-0.1.0.dist-info/METADATA
word4univer-0.1.0.dist-info/WHEEL
word4univer-0.1.0.dist-info/licenses/LICENSE.txt
word4univer-0.1.0.dist-info/RECORD
